{
  "id": "06fd386a-6d70-4957-ade6-119f53c76180",
  "prevId": "00000000-0000-0000-0000-000000000000",
  "version": "7",
  "dialect": "postgresql",
  "tables": {
    "public.domain_static": {
      "name": "domain_static",
      "schema": "",
      "columns": {
        "domain_id": {
          "name": "domain_id",
          "type": "serial",
          "primaryKey": false,
          "notNull": true
        },
        "total_requests": {
          "name": "total_requests",
          "type": "integer",
          "primaryKey": false,
          "notNull": true
        }
      },
      "indexes": {},
      "foreignKeys": {
        "domain_static_domain_id_domain_id_fk": {
          "name": "domain_static_domain_id_domain_id_fk",
          "tableFrom": "domain_static",
          "tableTo": "domain",
          "columnsFrom": [
            "domain_id"
          ],
          "columnsTo": [
            "id"
          ],
          "onDelete": "no action",
          "onUpdate": "no action"
        }
      },
      "compositePrimaryKeys": {},
      "uniqueConstraints": {},
      "policies": {},
      "checkConstraints": {},
      "isRLSEnabled": false
    },
    "public.domain": {
      "name": "domain",
      "schema": "",
      "columns": {
        "id": {
          "name": "id",
          "type": "serial",
          "primaryKey": true,
          "notNull": true
        },
        "user_id": {
          "name": "user_id",
          "type": "serial",
          "primaryKey": false,
          "notNull": true
        },
        "subdomain": {
          "name": "subdomain",
          "type": "varchar(64)",
          "primaryKey": false,
          "notNull": true
        },
        "hostname": {
          "name": "hostname",
          "type": "varchar(64)",
          "primaryKey": false,
          "notNull": true
        },
        "port": {
          "name": "port",
          "type": "integer",
          "primaryKey": false,
          "notNull": true
        }
      },
      "indexes": {},
      "foreignKeys": {
        "domain_user_id_user_id_fk": {
          "name": "domain_user_id_user_id_fk",
          "tableFrom": "domain",
          "tableTo": "user",
          "columnsFrom": [
            "user_id"
          ],
          "columnsTo": [
            "id"
          ],
          "onDelete": "no action",
          "onUpdate": "no action"
        }
      },
      "compositePrimaryKeys": {},
      "uniqueConstraints": {
        "domain_subdomain_unique": {
          "name": "domain_subdomain_unique",
          "nullsNotDistinct": false,
          "columns": [
            "subdomain"
          ]
        }
      },
      "policies": {},
      "checkConstraints": {},
      "isRLSEnabled": false
    },
    "public.user": {
      "name": "user",
      "schema": "",
      "columns": {
        "id": {
          "name": "id",
          "type": "serial",
          "primaryKey": true,
          "notNull": true
        },
        "name": {
          "name": "name",
          "type": "varchar(32)",
          "primaryKey": false,
          "notNull": true
        },
        "email": {
          "name": "email",
          "type": "varchar",
          "primaryKey": false,
          "notNull": true
        }
      },
      "indexes": {},
      "foreignKeys": {},
      "compositePrimaryKeys": {},
      "uniqueConstraints": {
        "user_email_unique": {
          "name": "user_email_unique",
          "nullsNotDistinct": false,
          "columns": [
            "email"
          ]
        }
      },
      "policies": {},
      "checkConstraints": {},
      "isRLSEnabled": false
    }
  },
  "enums": {},
  "schemas": {},
  "sequences": {},
  "roles": {},
  "policies": {},
  "views": {},
  "_meta": {
    "columns": {},
    "schemas": {},
    "tables": {}
  }
}